{"level":"info","ts":"2026-04-01T23:56:52.258+0300","msg":"Configuration loaded from environment"}
{"level":"error","ts":"2026-04-01T23:56:52.768+0300","msg":"Failed to drop table","error":"ОШИБКА: удалить объект таблица users нельзя, так как от него зависят другие объекты (SQLSTATE 2BP01)","stacktrace":"main.(*Logger).Error\n\tC:/Users/IGMA/Desktop/GitRepo/music_fed364847/go_service/logger.go:49\nmain.NewConnect\n\tC:/Users/IGMA/Desktop/GitRepo/music_fed364847/go_service/db_work.go:44\nmain.initDB\n\tC:/Users/IGMA/Desktop/GitRepo/music_fed364847/go_service/init.go:24\nmain.init.0\n\tC:/Users/IGMA/Desktop/GitRepo/music_fed364847/go_service/main.go:12\nruntime.doInit1\n\tC:/Program Files/Go/src/runtime/proc.go:7670\nruntime.doInit\n\tC:/Program Files/Go/src/runtime/proc.go:7637\nruntime.main\n\tC:/Program Files/Go/src/runtime/proc.go:256"}
{"level":"info","ts":"2026-04-01T23:56:52.778+0300","msg":"User storage created"}
{"level":"info","ts":"2026-04-01T23:56:52.779+0300","msg":"Database connected successfully"}
